flask_smorest-stubs/METADATA.toml
flask_smorest-stubs/__init__.pyi
flask_smorest-stubs/arguments.pyi
flask_smorest-stubs/blueprint.pyi
flask_smorest-stubs/error_handler.pyi
flask_smorest-stubs/etag.pyi
flask_smorest-stubs/exceptions.pyi
flask_smorest-stubs/fields.pyi
flask_smorest-stubs/pagination.pyi
flask_smorest-stubs/response.pyi
flask_smorest-stubs/utils.pyi
flask_smorest-stubs/spec/__init__.pyi
flask_smorest-stubs/spec/constants.pyi
flask_smorest-stubs/spec/field_converters.pyi
flask_smorest-stubs/spec/plugins.pyi
types_smorest-1.1.2.dist-info/LICENSE
types_smorest-1.1.2.dist-info/METADATA
types_smorest-1.1.2.dist-info/WHEEL
types_smorest-1.1.2.dist-info/top_level.txt
types_smorest-1.1.2.dist-info/RECORD
