Metadata-Version: 2.1
Name: types-smorest
Version: 1.1.2
Summary: Type Stubs for flask-smorest
Home-page: https://github.com/cex-solutions/types-smorest
Author: Binovate Labs
Author-email: cex-dev@binovate.com
License: GPLv3
Project-URL: Bug Reports, https://github.com/cex-solutions/types-smorest/issues
Project-URL: Source, https://github.com/cex-solutions/types-smorest
Keywords: flask flask-smorest smorest stubs
Classifier: Development Status :: 3 - Alpha
Classifier: Framework :: Flask
Classifier: Intended Audience :: Developers
Classifier: License :: OSI Approved :: GNU General Public License v3 or later (GPLv3+)
Classifier: Typing :: Stubs Only
Classifier: Programming Language :: Python :: 3 :: Only
Classifier: Programming Language :: Python :: 3.7
Classifier: Programming Language :: Python :: 3.8
Classifier: Programming Language :: Python :: 3.9
Classifier: Programming Language :: Python :: 3.10
Requires-Python: >=3.7, <4
License-File: LICENSE
Provides-Extra: dev
Requires-Dist: types-flask (==1.1.6) ; extra == 'dev'
Requires-Dist: marshmallow (==3.19.0) ; extra == 'dev'
Requires-Dist: apispec (==5.2.2) ; extra == 'dev'
Requires-Dist: flask (==2.2.2) ; extra == 'dev'
Requires-Dist: werkzeug (==2.2.2) ; extra == 'dev'
Requires-Dist: mypy (==0.991) ; extra == 'dev'
Requires-Dist: pipenv-setup (==3.2.0) ; extra == 'dev'
Requires-Dist: twine (==4.0.2) ; extra == 'dev'
